tweeterpy/__init__.py
tweeterpy/api_util.py
tweeterpy/config.py
tweeterpy/constants.py
tweeterpy/logging_util.py
tweeterpy/login.py
tweeterpy/login_util.py
tweeterpy/request_util.py
tweeterpy/session_util.py
tweeterpy/tweeterpy.py
tweeterpy/updater.py
tweeterpy/util.py
tweeterpy/tid/__init__.py
tweeterpy/tid/cubic_curve.py
tweeterpy/tid/interpolate.py
tweeterpy/tid/rotation.py
tweeterpy/tid/transaction.py
tweeterpy/tid/util.py
tweeterpy/utils/__init__.py
tweeterpy/utils/logging.py
tweeterpy/utils/request.py
tweeterpy/utils/session.py
tweeterpy-2.0.14.dist-info/LICENSE
tweeterpy-2.0.14.dist-info/METADATA
tweeterpy-2.0.14.dist-info/WHEEL
tweeterpy-2.0.14.dist-info/top_level.txt
tweeterpy-2.0.14.dist-info/RECORD
