Metadata-Version: 2.1
Name: tweeterpy
Version: 2.0.14
Summary: TweeterPy is a python library to extract data from Twitter. TweeterPy API lets you scrape data from a user's profile like username, userid, bio, followers/followings list, profile media, tweets, etc.
Home-page: https://github.com/iSarabjitDhiman/TweeterPy
Author: Sarabjit Dhiman
Author-email: hello@sarabjitdhiman.com
License: MIT
Keywords: tweeterpy,twitter scraper,tweet scraper,twitter data extraction,twitter api,twitter python,tweet api,tweetpy
Classifier: Development Status :: 3 - Alpha
Classifier: Intended Audience :: End Users/Desktop
Classifier: Intended Audience :: Developers
Classifier: Operating System :: Microsoft :: Windows
Classifier: Operating System :: MacOS :: MacOS X
Classifier: Operating System :: Unix
Classifier: License :: OSI Approved :: MIT License
Classifier: Topic :: Software Development :: Build Tools
Classifier: Programming Language :: Python :: 3
Requires-Python: >=3
License-File: LICENSE
Requires-Dist: beautifulsoup4==4.12.2
Requires-Dist: curl-cffi==0.13.0
Requires-Dist: demjson3==3.0.6
Requires-Dist: lxml==5.2.2
Requires-Dist: pyotp==2.9.0
Requires-Dist: XClientTransaction==1.0.1
